loeffler_1D_DCT/loeffler_1d.v
module loeffler_1d(clk, rstn, in, out, state);

parameter max_size = 12;

input clk, rstn;
input [1:0] state;
input [7:0] in;
output reg [max_size-1:0] out;

reg [3:0] counter1, counter4;
reg signed [max_size-1:0] o0, o1, o2, o4, o6, o7;
reg signed [21:0] o3, o5;
reg signed [max_size-1:0] s10, s11, s12, s13, s14, s15, s16, s17;
reg signed [max_size-1:0] s20, s21, s22, s23;
reg signed [21:0] s24, s25, s26, s27, s32, s33;
reg signed [max_size-1:0] s30, s31, s34, s35, s36, s37;
wire signed [21:0] tmp3,  tmp6,  tmp9;
wire signed [21:0] tmp4, tmp5, tmp7, tmp8, tmp1, tmp2;
reg [7:0] in_mem [0:7];
reg [11:0] out_mem [0:7];

//b sin //a cos   //中間的a和m代表加和減
//b-a sin - cos   //sq表示有根號2
//b+a sin + cos   //數字表示對應的kcn n數值

parameter c1as1 = 1204;   
parameter s1mc1 = -804;    
parameter c1 = 1004;     
parameter c3as3 = 1420;  
parameter s3mc3 = -282;     
parameter c3 = 851;     
parameter sqc1as1 = 1892;
parameter sqs1mc1 = 784;
parameter sqc1 = 554;   
parameter sq2 = 1448; 


always @(posedge clk) begin
    if(rstn == 0) begin
        counter1 <= 0;       
    end else if(state == 0)begin
        in_mem[counter1] <= in;
        counter1 <= counter1 + 1;
    end else begin
        in_mem[counter1] <= in_mem[counter1];
        counter1 <= counter1;
    end
end


//stage = 1/////////////////////////////////////////////////////////////////////

always @(posedge clk) begin
    if(state == 1) begin
        s10 <= in_mem[0] + in_mem[7];
        s17 <= in_mem[0] - in_mem[7];
        s11 <= in_mem[1] + in_mem[6];
        s16 <= in_mem[1] - in_mem[6];
        s12 <= in_mem[2] + in_mem[5];
        s15 <= in_mem[2] - in_mem[5];
        s13 <= in_mem[3] + in_mem[4];
        s14 <= in_mem[3] - in_mem[4];
    end
end

//stage = 2/////////////////////////////////////////////////////////////////////


assign tmp4 = (s17 * s3mc3);
assign tmp5 = (s14 * c3as3);
assign tmp7 = (s16 * s1mc1);
assign tmp8 = (s15 * c1as1);
assign tmp9 = (s15 + s16) * c1;
assign tmp6 = (s17 + s14) * c3;

always @(posedge clk) begin
    s20 <= s10 + s13;
    s23 <= s10 - s13;
    s21 <= s11 + s12;
    s22 <= s11 - s12;
    s24 <= (tmp4 + tmp6) >> 10;
    s27 <= (tmp6 - tmp5) >> 10;
    s25 <= (tmp7 + tmp9) >> 10;
    s26 <= (tmp9 - tmp8) >> 10;
end

//stage = 3/////////////////////////////////////////////////////////////////////

assign tmp1 = (s23 * sqs1mc1);
assign tmp2 = (s22 * sqc1as1);
assign tmp3 = (s22 + s23) * sqc1;

always @(posedge clk) begin
    s30 <= s20 + s21;
    s31 <= s20 - s21;
    s32 <= (tmp1 + tmp3) >> 10;
    s33 <= (tmp3 - tmp2) >> 10;
    s34 <= s24 + s26;
    s36 <= s24 - s26;
    s37 <= s27 + s25;
    s35 <= s27 - s25;
end

//stage = 4/////////////////////////////////////////////////////////////////////

always @(posedge clk) begin
    o0 <= s30;
    o4 <= s31;
    o2 <= s32;
    o6 <= s33;
    o1 <= s37 + s34;
    o7 <= s37 - s34;
    o3 <= (s35 * sq2) >> 10;
    o5 <= (s36 * sq2) >> 10;
end

always @(posedge clk) begin
    if(state == 2) begin
        out_mem[0] <= o0;
        out_mem[1] <= o1;
        out_mem[2] <= o2;
        out_mem[3] <= o3;
        out_mem[4] <= o4;
        out_mem[5] <= o5;
        out_mem[6] <= o6;
        out_mem[7] <= o7;
    end
end

always @(posedge clk) begin
    if(state == 3) begin
        out <= out_mem[counter4];
        counter4 <= counter4 + 1;
    end else begin
        counter4 <= 0;
    end
end


endmodule

DIC_loeffler_1D_DFT/loeffler_1d_test.v
`timescale 1ns/1ns
module stimulus_1ddct;

parameter clk_time = 5;
parameter max_size = 16; 

wire [11:0] out;


reg rstn, clk;
reg [1:0] state;
reg [7:0] in;


integer i, j;
integer handle1;

loeffler_1d dct_1d (clk, rstn, in, out, state);
 
reg [7:0] mem0 [0:63];
// reg [7:0] mem0 [0:63];
  
initial
begin
	clk=0;
	forever 
	#clk_time clk=~clk;	//Set clock with a period 10 units  5+5 10ns => 100Mhz
end
  
initial
begin

    //handle1 = $fopen("out.txt");
    // $readmemh("hex.txt", mem0);
    $readmemh("hex.txt", mem0);
    
    rstn = 1'b0;
    i = 0;
	state = 0;
    #10;
    rstn = 1'b1;
    
    for (i = 0; i <= 64; i = i + 1) begin	  
		if(i % 8 == 0)
		begin
			state = 1;
			#10;
			state = 2;
			#50;
			rstn = 0;
			state = 3;
			#100;
		end
		rstn = 1;
		state = 0;
		in = mem0[i];
		#10;
    end

	state = 0;
	// for (i = 0; i < 63; i = i + 8)
    // begin	  
	// 	win0 = mem0[i];
	// 	win1 = mem0[i+1];
	// 	win2 = mem0[i+2]; 
	// 	win3 = mem0[i+3]; 
	// 	win4 = mem0[i+4]; 
	// 	win5 = mem0[i+5]; 
	// 	win6 = mem0[i+6]; 
	// 	win7 = mem0[i+7]; 
	// 	#10;
    // end

	#10;

    //$fdisplay(handle1," %d, %d, %d, %d, %d, %d, %d, %d,", out0, out1, out2, out3, out4, out5, out6, out7);
	
	//#200 $fclose(handle1);
    #10 $finish; 
         
end

initial begin
	$dumpfile("1d_DCT.vcd");
    $dumpvars(0, stimulus_1ddct);
end

endmodule

loeffler_1D_DCT/1d_DCT.vcd
$date
	Tue May 28 15:42:46 2024
$end
$version
	Icarus Verilog
$end
$timescale
	1ns
$end
$scope module stimulus_1ddct $end
$var wire 12 ! out [11:0] $end
$var reg 1 " clk $end
$var reg 8 # in [7:0] $end
$var reg 1 $ rstn $end
$var reg 2 % state [1:0] $end
$var integer 32 & i [31:0] $end
$scope module dct_1d $end
$var wire 1 " clk $end
$var wire 8 ' in [7:0] $end
$var wire 1 $ rstn $end
$var wire 2 ( state [1:0] $end
$var wire 22 ) tmp9 [21:0] $end
$var wire 22 * tmp8 [21:0] $end
$var wire 22 + tmp7 [21:0] $end
$var wire 22 , tmp6 [21:0] $end
$var wire 22 - tmp5 [21:0] $end
$var wire 22 . tmp4 [21:0] $end
$var wire 22 / tmp3 [21:0] $end
$var wire 22 0 tmp2 [21:0] $end
$var wire 22 1 tmp1 [21:0] $end
$var reg 4 2 counter1 [3:0] $end
$var reg 4 3 counter4 [3:0] $end
$var reg 12 4 o0 [11:0] $end
$var reg 12 5 o1 [11:0] $end
$var reg 12 6 o2 [11:0] $end
$var reg 22 7 o3 [21:0] $end
$var reg 12 8 o4 [11:0] $end
$var reg 22 9 o5 [21:0] $end
$var reg 12 : o6 [11:0] $end
$var reg 12 ; o7 [11:0] $end
$var reg 12 < out [11:0] $end
$var reg 12 = s10 [11:0] $end
$var reg 12 > s11 [11:0] $end
$var reg 12 ? s12 [11:0] $end
$var reg 12 @ s13 [11:0] $end
$var reg 12 A s14 [11:0] $end
$var reg 12 B s15 [11:0] $end
$var reg 12 C s16 [11:0] $end
$var reg 12 D s17 [11:0] $end
$var reg 12 E s20 [11:0] $end
$var reg 12 F s21 [11:0] $end
$var reg 12 G s22 [11:0] $end
$var reg 12 H s23 [11:0] $end
$var reg 22 I s24 [21:0] $end
$var reg 22 J s25 [21:0] $end
$var reg 22 K s26 [21:0] $end
$var reg 22 L s27 [21:0] $end
$var reg 12 M s30 [11:0] $end
$var reg 12 N s31 [11:0] $end
$var reg 22 O s32 [21:0] $end
$var reg 22 P s33 [21:0] $end
$var reg 12 Q s34 [11:0] $end
$var reg 12 R s35 [11:0] $end
$var reg 12 S s36 [11:0] $end
$var reg 12 T s37 [11:0] $end
$upscope $end
$upscope $end
$enddefinitions $end
#0
$dumpvars
bx T
bx S
bx R
bx Q
bx P
bx O
bx N
bx M
bx L
bx K
bx J
bx I
bx H
bx G
bx F
bx E
bx D
bx C
bx B
bx A
bx @
bx ?
bx >
bx =
bx <
bx ;
bx :
bx 9
bx 8
bx 7
bx 6
bx 5
bx 4
bx 3
bx 2
bx 1
bx 0
bx /
bx .
bx -
bx ,
bx +
bx *
bx )
b0 (
bx '
b0 &
b0 %
0$
bx #
0"
bx !
$end
#5
b0 2
b0xxxxxxxxxxxx K
b0xxxxxxxxxxxx J
b0xxxxxxxxxxxx L
b0xxxxxxxxxxxx I
b0xxxxxxxxxxxx P
b0xxxxxxxxxxxx O
b0 3
1"
#10
0"
b1 %
b1 (
1$
#15
1"
#20
0"
b10 %
b10 (
#25
1"
#30
0"
#35
1"
#40
0"
#45
1"
#50
0"
#55
1"
#60
0"
#65
1"
#70
0"
b11 %
b11 (
0$
#75
b1 3
1"
#80
0"
#85
b10 3
1"
#90
0"
#95
b11 3
1"
#100
0"
#105
b100 3
1"
#110
0"
#115
b101 3
1"
#120
0"
#125
b110 3
1"
#130
0"
#135
b111 3
1"
#140
0"
#145
b1000 3
1"
#150
0"
#155
b1001 3
1"
#160
0"
#165
b1010 3
1"
#170
0"
b10001001 #
b10001001 '
b0 %
b0 (
1$
#175
b0 3
b1 2
1"
#180
0"
b1010001 #
b1010001 '
b1 &
#185
b10 2
1"
#190
0"
b10001001 #
b10001001 '
b10 &
#195
b11 2
1"
#200
0"
b10011101 #
b10011101 '
b11 &
#205
b100 2
1"
#210
0"
b1010 #
b1010 '
b100 &
#215
b101 2
1"
#220
0"
b0 #
b0 '
b101 &
#225
b110 2
1"
#230
0"
b110 &
#235
b111 2
1"
#240
0"
b1010 #
b1010 '
b111 &
#245
b1000 2
1"
#250
0"
b1 %
b1 (
b1000 &
#255
b110010111101100100 -
b111000111011010110 ,
b101000010001010100 *
b110101011011111000 )
b1111110000000110011100 +
b1111110111010000011010 .
b10010011 A
b10100111 @
b10001001 B
b10001001 ?
b1010001 C
b1010001 >
b1111111 D
b10010011 =
1"
#260
0"
b10 %
b10 (
#265
b1111100110001000100000 0
b1111110101101110001000 /
b1111111100001011000000 1
b110100 K
b10010110 J
b10111 L
b11000000 I
b111111001000 G
b11011010 F
b111111101100 H
b100111010 E
1"
#270
0"
#275
b111110000001 R
b10101101 T
b10001100 S
b11110100 Q
b111110 P
b111111000111 O
b1100000 N
b1000010100 M
1"
#280
0"
#285
b11000101 9
b1111111111111101001100 7
b111110111001 ;
b110100001 5
b111110 :
b111111000111 6
b1100000 8
b1000010100 4
1"
#290
0"
#295
1"
#300
0"
#305
1"
#310
0"
b11 %
b11 (
0$
#315
b1 3
b1000010100 !
b1000010100 <
b0 2
1"
#320
0"
#325
b10 3
b110100001 !
b110100001 <
1"
#330
0"
#335
b11 3
b111111000111 !
b111111000111 <
1"
#340
0"
#345
b100 3
b111101001100 !
b111101001100 <
1"
#350
0"
#355
b101 3
b1100000 !
b1100000 <
1"
#360
0"
#365
b110 3
b11000101 !
b11000101 <
1"
#370
0"
#375
b111 3
b111110 !
b111110 <
1"
#380
0"
#385
b1000 3
b111110111001 !
b111110111001 <
1"
#390
0"
#395
b1001 3
bx !
bx <
1"
#400
0"
#405
b1010 3
1"
#410
0"
b11001000 #
b11001000 '
b0 %
b0 (
1$
#415
b0 3
b1 2
1"
#420
0"
b10100110 #
b10100110 '
b1001 &
#425
b10 2
1"
#430
0"
b10110000 #
b10110000 '
b1010 &
#435
b11 2
1"
#440
0"
b11001000 #
b11001000 '
b1011 &
#445
b100 2
1"
#450
0"
b1010001 #
b1010001 '
b1100 &
#455
b101 2
1"
#460
0"
b1010 #
b1010 '
b1101 &
#465
b110 2
1"
#470
0"
b1110 &
#475
b111 2
1"
#480
0"
b1010001 #
b1010001 '
b1111 &
#485
b1000 2
1"
#490
0"
b1 %
b1 (
b10000 &
#495
b101001010000010100 -
b110000110010111000 *
b1111100001011000010000 +
b1001110111011011000 )
b1111110111110011101010 .
b110001011100101010 ,
b1110111 A
b100011001 @
b10100110 B
b10111010 ?
b10011100 C
b10110000 >
b1110111 D
b100011001 =
1"
#500
0"
b10 %
b10 (
#505
b1111111011011000011000 0
b0 1
b1111111110101001011100 /
b1111000 K
b11000001 J
b100000 L
b10100101 I
b111111110110 G
b101101010 F
b0 H
b1000110010 E
1"
#510
0"
#515
b111101011111 R
b11100001 T
b101101 S
b100011101 Q
b1101 P
b111111111010 O
b11001000 N
b1110011100 M
1"
#520
0"
#525
b111111 9
b1111111111111100011100 7
b111111000100 ;
b111111110 5
b1101 :
b111111111010 6
b11001000 8
b1110011100 4
1"
#530
0"
#535
1"
#540
0"
#545
1"
#550
0"
b11 %
b11 (
0$
#555
b1 3
b1110011100 !
b1110011100 <
b0 2
1"
#560
0"
#565
b10 3
b111111110 !
b111111110 <
1"
#570
0"
#575
b11 3
b111111111010 !
b111111111010 <
1"
#580
0"
#585
b100 3
b111100011100 !
b111100011100 <
1"
#590
0"
#595
b101 3
b11001000 !
b11001000 <
1"
#600
0"
#605
b110 3
b111111 !
b111111 <
1"
#610
0"
#615
b111 3
b1101 !
b1101 <
1"
#620
0"
#625
b1000 3
b111111000100 !
b111111000100 <
1"
#630
0"
#635
b1001 3
bx !
bx <
1"
#640
0"
#645
b1010 3
1"
#650
0"
b10011100 #
b10011100 '
b0 %
b0 (
1$
#655
b0 3
b1 2
1"
#660
0"
b10100110 #
b10100110 '
b10001 &
#665
b10 2
1"
#670
0"
b10110000 #
b10110000 '
b10010 &
#675
b11 2
1"
#680
0"
b10110101 #
b10110101 '
b10011 &
#685
b100 2
1"
#690
0"
b10001001 #
b10001001 '
b10100 &
#695
b101 2
1"
#700
0"
b10010011 #
b10010011 '
b10101 &
#705
b110 2
1"
#710
0"
b1101110 #
b1101110 '
b10110 &
#715
b111 2
1"
#720
0"
b1111000 #
b1111000 '
b10111 &
#725
b1000 2
1"
#730
0"
b1 %
b1 (
b11000 &
#735
b1111010000010000 -
b1000100001100100 *
b1111110101000000100000 +
b10100110101011100 )
b1111111101100001011000 .
b10000100111110000 ,
b101100 A
b100111110 @
b11101 B
b101000011 ?
b111000 C
b100010100 >
b100100 D
b100010100 =
1"
#740
0"
b10 %
b10 (
#745
b1111101010010010100100 0
b1111110111111101100000 1
b1111110011111101100110 /
b110001 K
b100111 J
b101 L
b111000 I
b111111010001 G
b1001010111 F
b111111010110 H
b1001010010 E
1"
#750
0"
#755
b111111011110 R
b101100 T
b111 S
b1101001 Q
b100110 P
b111110101111 O
b111111111011 N
b10010101001 M
1"
#760
0"
#765
b1001 9
b1111111111111111001111 7
b111111000011 ;
b10010101 5
b100110 :
b111110101111 6
b111111111011 8
b10010101001 4
1"
#770
0"
#775
1"
#780
0"
#785
1"
#790
0"
b11 %
b11 (
0$
#795
b1 3
b10010101001 !
b10010101001 <
b0 2
1"
#800
0"
#805
b10 3
b10010101 !
b10010101 <
1"
#810
0"
#815
b11 3
b111110101111 !
b111110101111 <
1"
#820
0"
#825
b100 3
b111111001111 !
b111111001111 <
1"
#830
0"
#835
b101 3
b111111111011 !
b111111111011 <
1"
#840
0"
#845
b110 3
b1001 !
b1001 <
1"
#850
0"
#855
b111 3
b100110 !
b100110 <
1"
#860
0"
#865
b1000 3
b111111000011 !
b111111000011 <
1"
#870
0"
#875
b1001 3
bx !
bx <
1"
#880
0"
#885
b1010 3
1"
#890
0"
b10010011 #
b10010011 '
b0 %
b0 (
1$
#895
b0 3
b1 2
1"
#900
0"
b10011000 #
b10011000 '
b11001 &
#905
b10 2
1"
#910
0"
b10011100 #
b10011100 '
b11010 &
#915
b11 2
1"
#920
0"
b10100001 #
b10100001 '
b11011 &
#925
b100 2
1"
#930
0"
b10001001 #
b10001001 '
b11100 &
#935
b101 2
1"
#940
0"
b10001101 #
b10001101 '
b11101 &
#945
b110 2
1"
#950
0"
b10010111 #
b10010111 '
b11110 &
#955
b111 2
1"
#960
0"
b10001001 #
b10001001 '
b11111 &
#965
b1000 2
1"
#970
0"
b1 %
b1 (
b100000 &
#975
b1000010100100000 -
b100011010001100 *
b1111111111110011011100 +
b11111011000000 )
b1111111111010011111100 .
b111000100000110 ,
b11000 A
b100101010 @
b1111 B
b100101001 ?
b1 C
b100101111 >
b1010 D
b100011100 =
1"
#980
0"
b10 %
b10 (
#985
b10110001011000 0
b1111111101010100100000 1
b1111111110111010110000 /
b111111111110 K
b1110 J
b111111111010 L
b11001 I
b110 G
b1001011000 F
b111111110010 H
b1001000110 E
1"
#990
0"
#995
b111111101100 R
b1000 T
b11011 S
b10111 Q
b111111110000 P
b111111110000 O
b111111101110 N
b10010011110 M
1"
#1000
0"
#1005
b100110 9
b1111111111111111100011 7
b111111110001 ;
b11111 5
b111111110000 :
b111111110000 6
b111111101110 8
b10010011110 4
1"
#1010
0"
#1015
1"
#1020
0"
#1025
1"
#1030
0"
b11 %
b11 (
0$
#1035
b1 3
b10010011110 !
b10010011110 <
b0 2
1"
#1040
0"
#1045
b10 3
b11111 !
b11111 <
1"
#1050
0"
#1055
b11 3
b111111110000 !
b111111110000 <
1"
#1060
0"
#1065
b100 3
b111111100011 !
b111111100011 <
1"
#1070
0"
#1075
b101 3
b111111101110 !
b111111101110 <
1"
#1080
0"
#1085
b110 3
b100110 !
b100110 <
1"
#1090
0"
#1095
b111 3
b111111110000 !
b111111110000 <
1"
#1100
0"
#1105
b1000 3
b111111110001 !
b111111110001 <
1"
#1110
0"
#1115
b1001 3
bx !
bx <
1"
#1120
0"
#1125
b1010 3
1"
#1130
0"
b10100110 #
b10100110 '
b0 %
b0 (
1$
#1135
b0 3
b1 2
1"
#1140
0"
b10011100 #
b10011100 '
b100001 &
#1145
b10 2
1"
#1150
0"
b10010111 #
b10010111 '
b100010 &
#1155
b11 2
1"
#1160
0"
b10010101 #
b10010101 '
b100011 &
#1165
b100 2
1"
#1170
0"
b10001011 #
b10001011 '
b100100 &
#1175
b101 2
1"
#1180
0"
b100101 &
#1185
b110 2
1"
#1190
0"
b10001001 #
b10001001 '
b100110 &
#1195
b111 2
1"
#1200
0"
b10100110 #
b10100110 '
b100111 &
#1205
b1000 2
1"
#1210
0"
b1 %
b1 (
b101000 &
#1215
b11011101111000 -
b11100001110000 *
b1111111100010001010100 +
b111100110010100 )
b0 .
b10000100111110 ,
b1010 A
b100100000 @
b1100 B
b100100010 ?
b10011 C
b100100101 >
b0 D
b101001100 =
1"
#1220
0"
b10 %
b10 (
#1225
b1011000101100 0
b1000011011000000 1
b110010110110110 /
b10000 K
b1111 J
b1000 I
b11 G
b1001000111 F
b101100 H
b1001101100 E
1"
#1230
0"
#1235
b111111101011 R
b1001 T
b111111111000 S
b11000 Q
b10011 P
b111011 O
b100101 N
b10010110011 M
1"
#1240
0"
#1245
b1111111111111111110100 9
b1111111111111111100010 7
b100001 5
b10011 :
b111011 6
b100101 8
b10010110011 4
1"
#1250
0"
#1255
1"
#1260
0"
#1265
1"
#1270
0"
b11 %
b11 (
0$
#1275
b1 3
b10010110011 !
b10010110011 <
b0 2
1"
#1280
0"
#1285
b10 3
b100001 !
b100001 <
1"
#1290
0"
#1295
b11 3
b111011 !
b111011 <
1"
#1300
0"
#1305
b100 3
b111111100010 !
b111111100010 <
1"
#1310
0"
#1315
b101 3
b100101 !
b100101 <
1"
#1320
0"
#1325
b110 3
b111111110100 !
b111111110100 <
1"
#1330
0"
#1335
b111 3
b10011 !
b10011 <
1"
#1340
0"
#1345
b1000 3
b111111110001 !
b111111110001 <
1"
#1350
0"
#1355
b1001 3
bx !
bx <
1"
#1360
0"
#1365
b1010 3
1"
#1370
0"
b10001110 #
b10001110 '
b0 %
b0 (
1$
#1375
b0 3
b1 2
1"
#1380
0"
b10001001 #
b10001001 '
b101001 &
#1385
b10 2
1"
#1390
0"
b1110101 #
b1110101 '
b101010 &
#1395
b11 2
1"
#1400
0"
b10001001 #
b10001001 '
b101011 &
#1405
b100 2
1"
#1410
0"
b10010011 #
b10010011 '
b101100 &
#1415
b101 2
1"
#1420
0"
b10001001 #
b10001001 '
b101101 &
#1425
b110 2
1"
#1430
0"
b10001011 #
b10001011 '
b101110 &
#1435
b111 2
1"
#1440
0"
b101111 &
#1445
b1000 2
1"
#1450
0"
b1 %
b1 (
b110000 &
#1455
b1111111100100010001000 -
b1111111010000111110000 *
b11001001000 +
b1111111010100110111000 )
b1111111111110010110010 .
b1111111110100010111011 ,
b111111110110 A
b100011100 @
b111111101100 B
b11111110 ?
b111111111110 C
b100010100 >
b11 D
b100011001 =
1"
#1460
0"
b10 %
b10 (
#1465
b1010001010011000 0
b1111111111011011010000 1
b10100100011110 /
b1 K
b111111101100 J
b1000 L
b111111111001 I
b10110 G
b1000010010 F
b111111111101 H
b1000110101 E
1"
#1470
0"
#1475
b11100 R
b111111110100 T
b111111111010 Q
b111111100001 P
b111 O
b100011 N
b10001000111 M
1"
#1480
0"
#1485
b100111 7
b111111111010 ;
b111111101110 5
b111111100001 :
b111 6
b100011 8
b10001000111 4
1"
#1490
0"
#1495
1"
#1500
0"
#1505
1"
#1510
0"
b11 %
b11 (
0$
#1515
b1 3
b10001000111 !
b10001000111 <
b0 2
1"
#1520
0"
#1525
b10 3
b111111101110 !
b111111101110 <
1"
#1530
0"
#1535
b11 3
b111 !
b111 <
1"
#1540
0"
#1545
b100 3
b100111 !
b100111 <
1"
#1550
0"
#1555
b101 3
b100011 !
b100011 <
1"
#1560
0"
#1565
b110 3
b111111110100 !
b111111110100 <
1"
#1570
0"
#1575
b111 3
b111111100001 !
b111111100001 <
1"
#1580
0"
#1585
b1000 3
b111111111010 !
b111111111010 <
1"
#1590
0"
#1595
b1001 3
bx !
bx <
1"
#1600
0"
#1605
b1010 3
1"
#1610
0"
b10001001 #
b10001001 '
b0 %
b0 (
1$
#1615
b0 3
b1 2
1"
#1620
0"
b10000100 #
b10000100 '
b110001 &
#1625
b10 2
1"
#1630
0"
b10001001 #
b10001001 '
b110010 &
#1635
b11 2
1"
#1640
0"
b10100110 #
b10100110 '
b110011 &
#1645
b100 2
1"
#1650
0"
b10001001 #
b10001001 '
b110100 &
#1655
b101 2
1"
#1660
0"
b110101 &
#1665
b110 2
1"
#1670
0"
b1111111 #
b1111111 '
b110110 &
#1675
b111 2
1"
#1680
0"
b10001001 #
b10001001 '
b110111 &
#1685
b1000 2
1"
#1690
0"
b1 %
b1 (
b111000 &
#1695
b1010000011011100 -
b0 *
b1111111111000001001100 +
b1001110011100 )
b0 .
b110000001100111 ,
b11101 A
b100101111 @
b0 B
b100010010 ?
b101 C
b100000011 >
b0 D
b100010010 =
1"
#1700
0"
b10 %
b10 (
#1705
b1111111001000100100100 0
b1111111010011100110000 1
b1111111010000011001000 /
b100 K
b0 J
b111111101111 L
b11000 I
b111111110001 G
b1000010101 F
b111111100011 H
b1001000001 E
1"
#1710
0"
#1715
b111111101111 R
b111111101111 T
b10100 S
b11100 Q
b11 P
b111111010001 O
b101100 N
b10001010110 M
1"
#1720
0"
#1725
b11100 9
b1111111111111111100111 7
b111111010011 ;
b1011 5
b11 :
b111111010001 6
b101100 8
b10001010110 4
1"
#1730
0"
#1735
1"
#1740
0"
#1745
1"
#1750
0"
b11 %
b11 (
0$
#1755
b1 3
b10001010110 !
b10001010110 <
b0 2
1"
#1760
0"
#1765
b10 3
b1011 !
b1011 <
1"
#1770
0"
#1775
b11 3
b111111010001 !
b111111010001 <
1"
#1780
0"
#1785
b100 3
b111111100111 !
b111111100111 <
1"
#1790
0"
#1795
b101 3
b101100 !
b101100 <
1"
#1800
0"
#1805
b110 3
b11100 !
b11100 <
1"
#1810
0"
#1815
b111 3
b11 !
b11 <
1"
#1820
0"
#1825
b1000 3
b111111010011 !
b111111010011 <
1"
#1830
0"
#1835
b1001 3
bx !
bx <
1"
#1840
0"
#1845
b1010 3
1"
#1850
0"
b10100110 #
b10100110 '
b0 %
b0 (
1$
#1855
b0 3
b1 2
1"
#1860
0"
b10001001 #
b10001001 '
b111001 &
#1865
b10 2
1"
#1870
0"
b10100110 #
b10100110 '
b111010 &
#1875
b11 2
1"
#1880
0"
b111011 &
#1885
b100 2
1"
#1890
0"
b10011100 #
b10011100 '
b111100 &
#1895
b101 2
1"
#1900
0"
b10001001 #
b10001001 '
b111101 &
#1905
b110 2
1"
#1910
0"
b111110 &
#1915
b111 2
1"
#1920
0"
b1111111 #
b1111111 '
b111111 &
#1925
b1000 2
1"
#1930
0"
b1 %
b1 (
b1000000 &
#1935
b11011101111000 -
b1000100001100100 *
b0 +
b111000110111100 )
b1111111101010100001010 .
b1010001011100011 ,
b1010 A
b101000010 @
b11101 B
b100101111 ?
b0 C
b100010010 >
b100111 D
b100100101 =
1"
#1940
0"
b10 %
b10 (
#1945
b1111110010100110101100 0
b1111111000001001111100 /
b111111111010 K
b11100 J
b11010 L
b11101 I
b111111100011 G
b1001000001 F
b1001100111 E
1"
#1950
0"
#1955
b111111111110 R
b110110 T
b100011 S
b10111 Q
b10110 P
b111111001010 O
b100110 N
b10010101000 M
1"
#1960
0"
#1965
b110001 9
b1111111111111111111101 7
b11111 ;
b1001101 5
b10110 :
b111111001010 6
b100110 8
b10010101000 4
1"
#1970
0"
#1975
1"
#1980
0"
#1985
1"
#1990
0"
b11 %
b11 (
0$
#1995
b1 3
b10010101000 !
b10010101000 <
b0 2
1"
#2000
0"
#2005
b10 3
b1001101 !
b1001101 <
1"
#2010
0"
#2015
b11 3
b111111001010 !
b111111001010 <
1"
#2020
0"
#2025
b100 3
b111111111101 !
b111111111101 <
1"
#2030
0"
#2035
b101 3
b100110 !
b100110 <
1"
#2040
0"
#2045
b110 3
b110001 !
b110001 <
1"
#2050
0"
#2055
b111 3
b10110 !
b10110 <
1"
#2060
0"
#2065
b1000 3
b11111 !
b11111 <
1"
#2070
0"
#2075
b1001 3
bx !
bx <
1"
#2080
0"
#2085
b1010 3
1"
#2090
0"
bx #
bx '
b0 %
b0 (
1$
#2095
b0 3
b1 2
1"
#2100
0"
b1000001 &
#2105
b10 2
1"
#2110
0"
#2115
b11 2
1"
